nemo_curator/__init__.py
nemo_curator/config.py
nemo_curator/package_info.py
nemo_curator/backends/__init__.py
nemo_curator/backends/base.py
nemo_curator/backends/utils.py
nemo_curator/backends/experimental/__init__.py
nemo_curator/backends/experimental/utils.py
nemo_curator/backends/experimental/ray_actor_pool/__init__.py
nemo_curator/backends/experimental/ray_actor_pool/adapter.py
nemo_curator/backends/experimental/ray_actor_pool/executor.py
nemo_curator/backends/experimental/ray_actor_pool/raft_adapter.py
nemo_curator/backends/experimental/ray_actor_pool/shuffle_adapter.py
nemo_curator/backends/experimental/ray_actor_pool/utils.py
nemo_curator/backends/experimental/ray_data/__init__.py
nemo_curator/backends/experimental/ray_data/adapter.py
nemo_curator/backends/experimental/ray_data/executor.py
nemo_curator/backends/experimental/ray_data/utils.py
nemo_curator/backends/internal/__init__.py
nemo_curator/backends/internal/raft/__init__.py
nemo_curator/backends/internal/raft/ray_comms.py
nemo_curator/backends/xenna/__init__.py
nemo_curator/backends/xenna/adapter.py
nemo_curator/backends/xenna/executor.py
nemo_curator/core/__init__.py
nemo_curator/core/client.py
nemo_curator/core/constants.py
nemo_curator/core/utils.py
nemo_curator/metrics/__init__.py
nemo_curator/metrics/constants.py
nemo_curator/metrics/start_prometheus_grafana.py
nemo_curator/metrics/utils.py
nemo_curator/models/__init__.py
nemo_curator/models/aesthetics.py
nemo_curator/models/base.py
nemo_curator/models/clip.py
nemo_curator/models/cosmos_embed1.py
nemo_curator/models/internvideo2_mm.py
nemo_curator/models/nsfw.py
nemo_curator/models/prompt_formatter.py
nemo_curator/models/qwen_lm.py
nemo_curator/models/qwen_vl.py
nemo_curator/models/transnetv2.py
nemo_curator/pipeline/__init__.py
nemo_curator/pipeline/pipeline.py
nemo_curator/stages/__init__.py
nemo_curator/stages/base.py
nemo_curator/stages/client_partitioning.py
nemo_curator/stages/file_partitioning.py
nemo_curator/stages/function_decorators.py
nemo_curator-1.0.0.dist-info/licenses/LICENSE
nemo_curator-1.0.0.dist-info/METADATA
nemo_curator-1.0.0.dist-info/WHEEL
nemo_curator-1.0.0.dist-info/top_level.txt
nemo_curator-1.0.0.dist-info/RECORD
