Metadata-Version: 2.4
Name: nemo-curator
Version: 1.0.0
Summary: Scalable Data Preprocessing Tool for Training Large Language Models
Author-email: Ayush Dattagupta <adattagupta@nvidia.com>, Abhinav Garg <abhgarg@nvidia.com>, Praateek Mahajan <praateekm@nvidia.com>, Sarah Yurick <syurick@nvidia.com>, Vibhu Jawa <vjawa@nvidia.com>
Requires-Python: <3.13,>=3.10
License-File: LICENSE
Requires-Dist: absl-py<3.0.0,>=2.0.0
Requires-Dist: comment_parser
Requires-Dist: cosmos-xenna==0.1.2
Requires-Dist: fsspec
Requires-Dist: jieba==0.42.1
Requires-Dist: loguru
Requires-Dist: mecab-python3
Requires-Dist: pandas>=2.1.0
Requires-Dist: pyarrow
Requires-Dist: ray[data,default]>=2.49
Requires-Dist: torch
Requires-Dist: transformers==4.55.2
Provides-Extra: cuda12
Requires-Dist: gpustat; extra == "cuda12"
Requires-Dist: pynvml; extra == "cuda12"
Provides-Extra: deduplication-cuda12
Requires-Dist: cudf-cu12==25.6.*; extra == "deduplication-cuda12"
Requires-Dist: cugraph-cu12==25.6.*; extra == "deduplication-cuda12"
Requires-Dist: cuml-cu12==25.6.*; extra == "deduplication-cuda12"
Requires-Dist: nx-cugraph-cu12==25.6.*; extra == "deduplication-cuda12"
Requires-Dist: pylibraft-cu12==25.6.*; extra == "deduplication-cuda12"
Requires-Dist: raft-dask-cu12==25.6.*; extra == "deduplication-cuda12"
Requires-Dist: rapidsmpf-cu12==25.6.*; extra == "deduplication-cuda12"
Provides-Extra: audio-cpu
Requires-Dist: nemo_toolkit[asr]==2.4.0; extra == "audio-cpu"
Provides-Extra: audio-cuda12
Requires-Dist: nemo_curator[audio_cpu]; extra == "audio-cuda12"
Requires-Dist: nemo_curator[cuda12]; extra == "audio-cuda12"
Provides-Extra: image-cpu
Requires-Dist: torchvision; extra == "image-cpu"
Provides-Extra: image-cuda12
Requires-Dist: nemo_curator[image_cpu]; extra == "image-cuda12"
Requires-Dist: nemo_curator[cuda12]; extra == "image-cuda12"
Requires-Dist: nemo_curator[deduplication_cuda12]; extra == "image-cuda12"
Requires-Dist: nvidia-dali-cuda120; extra == "image-cuda12"
Provides-Extra: text-cpu
Requires-Dist: beautifulsoup4; extra == "text-cpu"
Requires-Dist: justext; extra == "text-cpu"
Requires-Dist: lxml; extra == "text-cpu"
Requires-Dist: pycld2; extra == "text-cpu"
Requires-Dist: resiliparse; extra == "text-cpu"
Requires-Dist: s5cmd; extra == "text-cpu"
Requires-Dist: trafilatura==2.0.0; extra == "text-cpu"
Requires-Dist: warcio; extra == "text-cpu"
Requires-Dist: fasttext==0.9.3; extra == "text-cpu"
Requires-Dist: sentencepiece; extra == "text-cpu"
Requires-Dist: mwparserfromhell==0.6.5; extra == "text-cpu"
Requires-Dist: peft; extra == "text-cpu"
Requires-Dist: ftfy==6.1.1; extra == "text-cpu"
Provides-Extra: text-cuda12
Requires-Dist: nemo_curator[cuda12]; extra == "text-cuda12"
Requires-Dist: nemo_curator[deduplication_cuda12]; extra == "text-cuda12"
Requires-Dist: nemo_curator[text_cpu]; extra == "text-cuda12"
Provides-Extra: video-cpu
Requires-Dist: av==13.1.0; extra == "video-cpu"
Requires-Dist: opencv-python; extra == "video-cpu"
Requires-Dist: torchvision; extra == "video-cpu"
Requires-Dist: einops; extra == "video-cpu"
Requires-Dist: easydict; extra == "video-cpu"
Provides-Extra: video-cuda12
Requires-Dist: nemo_curator[video_cpu]; extra == "video-cuda12"
Requires-Dist: nemo_curator[cuda12]; extra == "video-cuda12"
Requires-Dist: cvcuda_cu12; extra == "video-cuda12"
Requires-Dist: flash-attn<=2.8.3; (platform_machine == "x86_64" and platform_system != "Darwin") and extra == "video-cuda12"
Requires-Dist: pycuda; extra == "video-cuda12"
Requires-Dist: PyNvVideoCodec==2.0.2; (platform_machine == "x86_64" and platform_system != "Darwin") and extra == "video-cuda12"
Requires-Dist: torch<=2.8.0; extra == "video-cuda12"
Requires-Dist: torchaudio; extra == "video-cuda12"
Requires-Dist: vllm==0.10.2; (platform_machine == "x86_64" and platform_system != "Darwin") and extra == "video-cuda12"
Provides-Extra: all
Requires-Dist: nemo_curator[audio_cuda12]; extra == "all"
Requires-Dist: nemo_curator[image_cuda12]; extra == "all"
Requires-Dist: nemo_curator[text_cuda12]; extra == "all"
Requires-Dist: nemo_curator[video_cuda12]; extra == "all"
Dynamic: license-file
